gnosari_realtime/__init__.py
gnosari_realtime/client/__init__.py
gnosari_realtime/client/client.py
gnosari_realtime/core/__init__.py
gnosari_realtime/core/channel_manager.py
gnosari_realtime/core/schemas.py
gnosari_realtime/infrastructure/__init__.py
gnosari_realtime/infrastructure/database.py
gnosari_realtime/infrastructure/opensearch_client.py
gnosari_realtime/infrastructure/redis_client.py
gnosari_realtime/infrastructure/repositories.py
gnosari_realtime/server/__init__.py
gnosari_realtime/server/app.py
gnosari_realtime/server/auth.py
gnosari_realtime/server/config.py
gnosari_realtime/server/connection_manager.py
gnosari_realtime/server/main.py
gnosari_realtime-0.1.3.dist-info/METADATA
gnosari_realtime-0.1.3.dist-info/WHEEL
gnosari_realtime-0.1.3.dist-info/entry_points.txt
gnosari_realtime-0.1.3.dist-info/RECORD
