Metadata-Version: 2.3
Name: gnosari-realtime
Version: 0.1.3
Summary: Real-time WebSocket pub/sub server with optional AI processing
Author: Gnosari Team
Author-email: team@gnosari.com
Requires-Python: >=3.11,<4.0
Classifier: Programming Language :: Python :: 3
Classifier: Programming Language :: Python :: 3.11
Classifier: Programming Language :: Python :: 3.12
Classifier: Programming Language :: Python :: 3.13
Requires-Dist: alembic (>=1.17.0,<2.0.0)
Requires-Dist: asyncpg (>=0.30.0,<0.31.0)
Requires-Dist: colorama (>=0.4.6,<0.5.0)
Requires-Dist: httpx (>=0.28.1,<0.29.0)
Requires-Dist: opensearch-py (>=3.0.0,<4.0.0)
Requires-Dist: pydantic-settings (>=2.11.0,<3.0.0)
Requires-Dist: pydantic[email] (>=2.12.3,<3.0.0)
Requires-Dist: pyjwt[crypto] (>=2.10.1,<3.0.0)
Requires-Dist: python-multipart (>=0.0.20,<0.0.21)
Requires-Dist: redis (>=5.2.0,<6.5.0)
Requires-Dist: sqlalchemy[asyncio] (>=2.0.44,<3.0.0)
Requires-Dist: starlette (>=0.48.0,<0.49.0)
Requires-Dist: structlog (>=25.4.0,<26.0.0)
Requires-Dist: uvicorn[standard] (>=0.38.0,<0.39.0)
Requires-Dist: uvloop (>=0.22.1,<0.23.0)
Requires-Dist: websockets (>=15.0.1,<16.0.0)
